.coveragerc
.pylintrc
.testr.conf
AUTHORS
CONTRIBUTING.rst
ChangeLog
HACKING.rst
LICENSE
MANIFEST.in
README.rst
TESTING.rst
requirements.txt
run_tests.sh
setup.cfg
setup.py
test-requirements.txt
tox.ini
bsnstacklib/__init__.py
bsnstacklib/hooks.py
bsnstacklib.egg-info/PKG-INFO
bsnstacklib.egg-info/SOURCES.txt
bsnstacklib.egg-info/dependency_links.txt
bsnstacklib.egg-info/entry_points.txt
bsnstacklib.egg-info/not-zip-safe
bsnstacklib.egg-info/pbr.json
bsnstacklib.egg-info/top_level.txt
bsnstacklib/bsnlldp/__init__.py
bsnstacklib/bsnlldp/bsnlldp.py
bsnstacklib/bsnlldp/rhlib.py
bsnstacklib/bsnlldp/send_lldp.py
bsnstacklib/plugins/__init__.py
bsnstacklib/plugins/bigswitch/README
bsnstacklib/plugins/bigswitch/__init__.py
bsnstacklib/plugins/bigswitch/bsn_service_plugin.py
bsnstacklib/plugins/bigswitch/config.py
bsnstacklib/plugins/bigswitch/dhcp_driver.py
bsnstacklib/plugins/bigswitch/i18n.py
bsnstacklib/plugins/bigswitch/l3_router_plugin.py
bsnstacklib/plugins/bigswitch/plugin.py
bsnstacklib/plugins/bigswitch/routerrule_db.py
bsnstacklib/plugins/bigswitch/servermanager.py
bsnstacklib/plugins/bigswitch/utils.py
bsnstacklib/plugins/bigswitch/vcsversion.py
bsnstacklib/plugins/bigswitch/version.py
bsnstacklib/plugins/bigswitch/agent/__init__.py
bsnstacklib/plugins/bigswitch/agent/restproxy_agent.py
bsnstacklib/plugins/bigswitch/db/__init__.py
bsnstacklib/plugins/bigswitch/db/consistency_db.py
bsnstacklib/plugins/bigswitch/db/network_template_db.py
bsnstacklib/plugins/bigswitch/db/porttracker_db.py
bsnstacklib/plugins/bigswitch/db/reachability_test_db.py
bsnstacklib/plugins/bigswitch/db/routerrule_db.py
bsnstacklib/plugins/bigswitch/db/migration/__init__.py
bsnstacklib/plugins/bigswitch/db/migration/alembic_migrations/README
bsnstacklib/plugins/bigswitch/db/migration/alembic_migrations/__init__.py
bsnstacklib/plugins/bigswitch/db/migration/alembic_migrations/env.py
bsnstacklib/plugins/bigswitch/db/migration/alembic_migrations/script.py.mako
bsnstacklib/plugins/bigswitch/db/migration/alembic_migrations/versions/1086543dfc0f_update_column_type_for_testpath_result.py
bsnstacklib/plugins/bigswitch/db/migration/alembic_migrations/versions/1ef57200f387_testpath_modify_uniq_constraint.py
