Metadata-Version: 1.1
Name: bsnstacklib
Version: 20153.36.12
Summary: Big Switch Networks Plugins for OpenStack Networking
Home-page: http://www.bigswitch.com/
Author: Big Switch Networks
Author-email: support@bigswitch.com
License: UNKNOWN
Platform: UNKNOWN
Classifier: Environment :: OpenStack
Classifier: Intended Audience :: Information Technology
Classifier: Intended Audience :: System Administrators
Classifier: License :: OSI Approved :: Apache Software License
Classifier: Operating System :: POSIX :: Linux
Classifier: Programming Language :: Python
Classifier: Programming Language :: Python :: 2
Classifier: Programming Language :: Python :: 2.7
